optrace/raytrace.py
optrace-0.1.0.dist-info/LICENSE
optrace-0.1.0.dist-info/METADATA
optrace-0.1.0.dist-info/WHEEL
optrace-0.1.0.dist-info/top_level.txt
optrace-0.1.0.dist-info/RECORD
