Metadata-Version: 2.1
Name: optrace
Version: 0.1.0
Summary: 3D raytracer for optical simulations
Author-email: Patrick Müller <pmueller@physics.ucla.edu>
License: MIT License
Project-URL: download, https://pypi.org/project/optrace/#files
Project-URL: source, https://github.com/patmlr/optrace
Project-URL: tracker, https://github.com/patmlr/optrace/issues
Keywords: physics,optics,raytracing,simulation,laser spectroscopy
Classifier: Development Status :: 2 - Pre-Alpha
Classifier: Intended Audience :: Science/Research
Classifier: License :: OSI Approved :: MIT License
Classifier: Operating System :: Microsoft :: Windows
Classifier: Programming Language :: Python :: 3
Classifier: Programming Language :: Python :: 3 :: Only
Classifier: Topic :: Scientific/Engineering :: Physics
Requires-Python: >=3.8
License-File: LICENSE
Requires-Dist: numpy>=2.0.2
Requires-Dist: scipy>=1.13.1
Requires-Dist: qspec>=0.3.6
Requires-Dist: pyqt5>=5.15.11
Requires-Dist: pyqtgraph>=0.13.7
Requires-Dist: pyopengl>=3.1.7
